[
  {
    "full_name": "go-python/gopy",
    "stargazers_count": 1777,
    "open_issues_count": 48,
    "forks_count": 110
  },
  {
    "full_name": "zincsearch/zincsearch",
    "stargazers_count": 15841,
    "open_issues_count": 33,
    "forks_count": 690
  },
  {
    "full_name": "emirpasic/gods",
    "stargazers_count": 14844,
    "open_issues_count": 31,
    "forks_count": 1707
  },
  {
    "full_name": "opencost/opencost",
    "stargazers_count": 4422,
    "open_issues_count": 144,
    "forks_count": 486
  },
  {
    "full_name": "open-sauced/open-sauced",
    "stargazers_count": 899,
    "open_issues_count": 0,
    "forks_count": 821
  }
]