[
  {
    "full_name": "go-python/gopy",
    "stargazers_count": 2252,
    "open_issues_count": 65,
    "forks_count": 127
  },
  {
    "full_name": "zincsearch/zincsearch",
    "stargazers_count": 17595,
    "open_issues_count": 45,
    "forks_count": 763
  },
  {
    "full_name": "emirpasic/gods",
    "stargazers_count": 17213,
    "open_issues_count": 69,
    "forks_count": 1818
  },
  {
    "full_name": "opencost/opencost",
    "stargazers_count": 6108,
    "open_issues_count": 183,
    "forks_count": 696
  },
  {
    "full_name": "open-sauced/open-sauced",
    "stargazers_count": 956,
    "open_issues_count": 0,
    "forks_count": 1156
  }
]