[
  {
    "full_name": "go-python/gopy",
    "stargazers_count": 2185,
    "open_issues_count": 63,
    "forks_count": 121
  },
  {
    "full_name": "zincsearch/zincsearch",
    "stargazers_count": 17436,
    "open_issues_count": 45,
    "forks_count": 754
  },
  {
    "full_name": "emirpasic/gods",
    "stargazers_count": 16949,
    "open_issues_count": 67,
    "forks_count": 1805
  },
  {
    "full_name": "opencost/opencost",
    "stargazers_count": 5831,
    "open_issues_count": 108,
    "forks_count": 624
  },
  {
    "full_name": "open-sauced/open-sauced",
    "stargazers_count": 952,
    "open_issues_count": 0,
    "forks_count": 1135
  }
]