[
  {
    "full_name": "go-python/gopy",
    "stargazers_count": 1746,
    "open_issues_count": 54,
    "forks_count": 110
  },
  {
    "full_name": "zincsearch/zincsearch",
    "stargazers_count": 15618,
    "open_issues_count": 30,
    "forks_count": 678
  },
  {
    "full_name": "emirpasic/gods",
    "stargazers_count": 14606,
    "open_issues_count": 31,
    "forks_count": 1691
  },
  {
    "full_name": "opencost/opencost",
    "stargazers_count": 4293,
    "open_issues_count": 155,
    "forks_count": 470
  },
  {
    "full_name": "open-sauced/open-sauced",
    "stargazers_count": 897,
    "open_issues_count": 0,
    "forks_count": 766
  }
]