[
  {
    "full_name": "go-python/gopy",
    "stargazers_count": 2125,
    "open_issues_count": 59,
    "forks_count": 116
  },
  {
    "full_name": "zincsearch/zincsearch",
    "stargazers_count": 17223,
    "open_issues_count": 49,
    "forks_count": 745
  },
  {
    "full_name": "emirpasic/gods",
    "stargazers_count": 16710,
    "open_issues_count": 65,
    "forks_count": 1800
  },
  {
    "full_name": "opencost/opencost",
    "stargazers_count": 5608,
    "open_issues_count": 94,
    "forks_count": 592
  },
  {
    "full_name": "open-sauced/open-sauced",
    "stargazers_count": 945,
    "open_issues_count": 0,
    "forks_count": 1090
  }
]