[
  {
    "full_name": "go-python/gopy",
    "stargazers_count": 1490,
    "open_issues_count": 36,
    "forks_count": 95
  },
  {
    "full_name": "zinclabs/zinc",
    "stargazers_count": 13261,
    "open_issues_count": 84,
    "forks_count": 567
  },
  {
    "full_name": "emirpasic/gods",
    "stargazers_count": 13171,
    "open_issues_count": 25,
    "forks_count": 1546
  },
  {
    "full_name": "opencost/opencost",
    "stargazers_count": 3221,
    "open_issues_count": 144,
    "forks_count": 339
  },
  {
    "full_name": "open-sauced/open-sauced",
    "stargazers_count": 837,
    "open_issues_count": 9,
    "forks_count": 502
  }
]